compyte_kernel/__init__.py
compyte_kernel/lib.py
compyte_kernel-0.0.1a2.dist-info/LICENSE
compyte_kernel-0.0.1a2.dist-info/METADATA
compyte_kernel-0.0.1a2.dist-info/WHEEL
compyte_kernel-0.0.1a2.dist-info/top_level.txt
compyte_kernel-0.0.1a2.dist-info/RECORD
