Metadata-Version: 2.1
Name: compyte-kernel
Version: 0.0.1a2
Summary: A compute kernel
Home-page: https://github.com/automacoin/compyte-kernel
Author: AutomaCoin Devs
Author-email: alessio.proietti@protonmail.com
License: UNKNOWN
Project-URL: Bug Tracker, https://github.com/automacoin/compyte-kernel/issues
Platform: UNKNOWN
Classifier: Programming Language :: Python :: 3
Classifier: License :: OSI Approved :: Apache Software License
Classifier: Operating System :: OS Independent
Requires-Python: >=3.6
License-File: LICENSE
